analysis/high_performance/jax/__init__.py
analysis/high_performance/jax/cwt_jax.py
analysis/high_performance/jax/dfa_jax.py
analysis/high_performance/jax/dma_jax.py
analysis/high_performance/jax/gph_jax.py
analysis/high_performance/jax/higuchi_jax.py
analysis/high_performance/jax/mfdfa_jax.py
analysis/high_performance/jax/multifractal_wavelet_leaders_jax.py
analysis/high_performance/jax/periodogram_jax.py
analysis/high_performance/jax/rs_jax.py
analysis/high_performance/jax/wavelet_log_variance_jax.py
analysis/high_performance/jax/wavelet_variance_jax.py
analysis/high_performance/jax/wavelet_whittle_jax.py
analysis/high_performance/jax/whittle_jax.py
analysis/high_performance/numba/__init__.py
analysis/high_performance/numba/cwt_numba.py
analysis/high_performance/numba/dfa_numba.py
analysis/high_performance/numba/dma_numba.py
analysis/high_performance/numba/gph_numba.py
analysis/high_performance/numba/higuchi_numba.py
analysis/high_performance/numba/mfdfa_numba.py
analysis/high_performance/numba/multifractal_wavelet_leaders_numba.py
analysis/high_performance/numba/periodogram_numba.py
analysis/high_performance/numba/rs_numba.py
analysis/high_performance/numba/wavelet_log_variance_numba.py
analysis/high_performance/numba/wavelet_variance_numba.py
analysis/high_performance/numba/wavelet_whittle_numba.py
analysis/high_performance/numba/whittle_numba.py
analysis/machine_learning/__init__.py
analysis/machine_learning/base_ml_estimator.py
analysis/machine_learning/cnn_estimator.py
analysis/machine_learning/gradient_boosting_estimator.py
analysis/machine_learning/gru_estimator.py
analysis/machine_learning/lstm_estimator.py
analysis/machine_learning/neural_network_estimator.py
analysis/machine_learning/random_forest_estimator.py
analysis/machine_learning/svr_estimator.py
analysis/machine_learning/transformer_estimator.py
analysis/multifractal/mfdfa/mfdfa_estimator.py
analysis/multifractal/wavelet_leaders/multifractal_wavelet_leaders_estimator.py
data_exploratory_project-1.0.0.dist-info/licenses/LICENSE
data_exploratory_project-1.0.0.dist-info/METADATA
data_exploratory_project-1.0.0.dist-info/WHEEL
data_exploratory_project-1.0.0.dist-info/entry_points.txt
data_exploratory_project-1.0.0.dist-info/top_level.txt
data_exploratory_project-1.0.0.dist-info/RECORD
