Metadata-Version: 2.4
Name: data-exploratory-project
Version: 1.0.0
Summary: A comprehensive framework for long-range dependence estimation with synthetic data generation and analysis
Home-page: https://github.com/yourusername/DataExploratoryProject
Author: Your Name
Author-email: Your Name <your.email@example.com>
Maintainer-email: Your Name <your.email@example.com>
License: MIT
Project-URL: Homepage, https://github.com/yourusername/DataExploratoryProject
Project-URL: Documentation, https://github.com/yourusername/DataExploratoryProject#readme
Project-URL: Repository, https://github.com/yourusername/DataExploratoryProject
Project-URL: Bug Tracker, https://github.com/yourusername/DataExploratoryProject/issues
Keywords: long-range-dependence,hurst-exponent,fractional-calculus,time-series-analysis,synthetic-data,benchmarking,estimators,neural-networks,physics-informed,scientific-computing
Classifier: Development Status :: 5 - Production/Stable
Classifier: Intended Audience :: Science/Research
Classifier: Intended Audience :: Developers
Classifier: License :: OSI Approved :: MIT License
Classifier: Operating System :: OS Independent
Classifier: Programming Language :: Python :: 3
Classifier: Programming Language :: Python :: 3.8
Classifier: Programming Language :: Python :: 3.9
Classifier: Programming Language :: Python :: 3.10
Classifier: Programming Language :: Python :: 3.11
Classifier: Programming Language :: Python :: 3.12
Classifier: Topic :: Scientific/Engineering :: Mathematics
Classifier: Topic :: Scientific/Engineering :: Artificial Intelligence
Classifier: Topic :: Software Development :: Libraries :: Python Modules
Requires-Python: >=3.8
License-File: LICENSE
Requires-Dist: numpy>=1.21.0
Requires-Dist: scipy>=1.7.0
Requires-Dist: pandas>=1.3.0
Requires-Dist: matplotlib>=3.4.0
Requires-Dist: seaborn>=0.11.0
Requires-Dist: scikit-learn>=1.0.0
Requires-Dist: PyWavelets>=1.1.0
Requires-Dist: fastapi>=0.68.0
Requires-Dist: uvicorn>=0.15.0
Requires-Dist: sqlalchemy>=1.4.0
Requires-Dist: psycopg2-binary>=2.9.0
Provides-Extra: dev
Requires-Dist: pytest>=6.0; extra == "dev"
Requires-Dist: pytest-cov>=2.0; extra == "dev"
Requires-Dist: black>=21.0; extra == "dev"
Requires-Dist: flake8>=3.8; extra == "dev"
Requires-Dist: mypy>=0.800; extra == "dev"
Requires-Dist: pre-commit>=2.0; extra == "dev"
Provides-Extra: docs
Requires-Dist: sphinx>=4.0; extra == "docs"
Requires-Dist: sphinx-rtd-theme>=1.0; extra == "docs"
Requires-Dist: myst-parser>=0.15; extra == "docs"
Provides-Extra: full
Requires-Dist: jax>=0.3.0; extra == "full"
Requires-Dist: jaxlib>=0.3.0; extra == "full"
Requires-Dist: torch>=1.9.0; extra == "full"
Requires-Dist: numba>=0.56.0; extra == "full"
Dynamic: author
Dynamic: home-page
Dynamic: license-file
Dynamic: requires-python
